mvSPC/__init__.py
mvSPC/autoencoders/__init__.py
mvSPC/autoencoders/oae/__init__.py
mvSPC/autoencoders/oae/control_charts.py
mvSPC/autoencoders/oae/example.py
mvSPC/autoencoders/oae/model.py
mvSPC/autoencoders/oae/training.py
mvSPC/autoencoders/oae/utils.py
mvSPC/autoencoders/vae/__init__.py
mvSPC/autoencoders/vae/control_charts.py
mvSPC/autoencoders/vae/example.py
mvSPC/autoencoders/vae/explore.py
mvSPC/autoencoders/vae/training.py
mvSPC/autoencoders/vae/vae.py
mvSPC/baseSPC/__init__.py
mvSPC/baseSPC/constants.py
mvSPC/baseSPC/core.py
mvSPC/baseSPC/definitions.py
mvSPC/baseSPC/helpers.py
mvSPC/baseSPC/examples/__init__.py
mvSPC/baseSPC/examples/run_TEP_example.py
mvSPC/baseSPC/examples/run_feedpump_example.py
mvSPC/baseSPC/examples/run_multivariate_chart_examples.py
mvSPC/baseSPC/examples/run_univariate_chart_examples.py
mvSPC/baseSPC/tests/__init__.py
mvSPC/baseSPC/tests/conftest.py
mvSPC/baseSPC/tests/test_control_charts.py
mvSPC/baseSPC/tests/test_helpers.py
mvSPC/datasets/__init__.py
mvSPC/dynamicPCA/TEP.py
mvSPC/dynamicPCA/__init__.py
mvSPC/dynamicPCA/_modidx.py
mvSPC/dynamicPCA/analysis.py
mvSPC/dynamicPCA/corrmat.py
mvSPC/dynamicPCA/example.py
mvSPC/dynamicPCA/lag.py
mvSPC-1.0.17.dist-info/LICENSE
mvSPC-1.0.17.dist-info/METADATA
mvSPC-1.0.17.dist-info/WHEEL
mvSPC-1.0.17.dist-info/top_level.txt
mvSPC-1.0.17.dist-info/RECORD
